processors/__init__.py
processors/executor.py
service/__init__.py
service/keywords/__init__.py
service/keywords/models.py
service/keywords/parse.py
grebble_rpa-0.0.1.dist-info/METADATA
grebble_rpa-0.0.1.dist-info/WHEEL
grebble_rpa-0.0.1.dist-info/top_level.txt
grebble_rpa-0.0.1.dist-info/RECORD
