Metadata-Version: 2.1
Name: grebble-rpa
Version: 0.0.1
Summary: Grebble rpa desktop
Home-page: https://github.com/Grebble-team/rpa
Author: Grebble
Author-email: info@grebble.io
License: UNKNOWN
Platform: UNKNOWN
Requires-Dist: grebble-flow (==0.0.3.50)
Requires-Dist: rpaframework
Requires-Dist: robotframework-browser
Requires-Dist: rpaframework-dialogs
Requires-Dist: rpaframework-windows
